breadbin/__init__.py
breadbin-0.0.0a0.dev0.dist-info/METADATA
breadbin-0.0.0a0.dev0.dist-info/WHEEL
breadbin-0.0.0a0.dev0.dist-info/licenses/LICENSE
breadbin-0.0.0a0.dev0.dist-info/RECORD
