Metadata-Version: 2.3
Name: breadbin
Version: 0.0.0a0.dev0
Summary: ...
Project-URL: Documentation, http://breadbin.rtfd.io/
Project-URL: Homepage, https://github.com/thatgaypigeon/breadbin
Project-URL: Issues / Bugs, https://github.com/thatgaypigeon/breadbin/issues
Project-URL: PyPI, https://pypi.org/project/breadbin/
Project-URL: Support Server, https://discord.gg/MyPTZBH4Q8
Author-email: thatgaypigeon <rapidpigeon43@gmail.com>
License: The MIT License (MIT)
License-File: LICENSE
Keywords: breadbin,thatgaypigeon
Classifier: Topic :: Other/Nonlisted Topic
Classifier: Typing :: Typed
Requires-Python: >=3.8
